notion_objects/__init__.py
notion_objects/database.py
notion_objects/encode.py
notion_objects/objects.py
notion_objects/properties.py
notion_objects/rich_text.py
notion_objects/values.py
notion_objects-0.6.4.dist-info/licenses/LICENSE
notion_objects-0.6.4.dist-info/METADATA
notion_objects-0.6.4.dist-info/WHEEL
notion_objects-0.6.4.dist-info/top_level.txt
notion_objects-0.6.4.dist-info/RECORD
