Metadata-Version: 2.4
Name: notion-objects
Version: 0.6.4
Summary: A python library to work with objects retrieved from the notion API
Home-page: https://github.com/thrau/notion-objects
Author: Thomas Rausch
Author-email: thomas@thrau.at
License: Apache License 2.0
Classifier: License :: OSI Approved :: Apache Software License
Classifier: Development Status :: 4 - Beta
Classifier: Operating System :: OS Independent
Classifier: Programming Language :: Python :: 3
Classifier: Programming Language :: Python :: 3.8
Classifier: Programming Language :: Python :: 3.9
Classifier: Programming Language :: Python :: 3.10
Classifier: Programming Language :: Python :: 3.11
Classifier: Programming Language :: Python :: 3.12
License-File: LICENSE
Requires-Dist: python-dateutil>=2.8
Requires-Dist: notion-client>=1.0
Provides-Extra: test
Requires-Dist: coverage[toml]>=5.0; extra == "test"
Requires-Dist: pytest-cov>=2.7.1; extra == "test"
Requires-Dist: coveralls; extra == "test"
Requires-Dist: black>=22.1; extra == "test"
Requires-Dist: isort>=5.10; extra == "test"
Requires-Dist: pytest>=7.0; extra == "test"
Dynamic: license-file
